<annotation>
	<folder>images</folder>
	<filename>datum-04031.png</filename>
	<path>C:\Users\Lenovo-PC\OneDrive\Documents\To Annotate\images\datum-04031.png</path>
	<source>
		<database>Unknown</database>
	</source>
	<size>
		<width>1920</width>
		<height>1080</height>
		<depth>3</depth>
	</size>
	<segmented>0</segmented>
	<object>
		<name>tree branch</name>
		<pose>Unspecified</pose>
		<truncated>0</truncated>
		<difficult>0</difficult>
		<bndbox>
			<xmin>785</xmin>
			<ymin>657</ymin>
			<xmax>983</xmax>
			<ymax>1005</ymax>
		</bndbox>
	</object>
	<object>
		<name>leaf</name>
		<pose>Unspecified</pose>
		<truncated>0</truncated>
		<difficult>0</difficult>
		<bndbox>
			<xmin>1044</xmin>
			<ymin>1000</ymin>
			<xmax>1069</xmax>
			<ymax>1037</ymax>
		</bndbox>
	</object>
	<object>
		<name>leaf</name>
		<pose>Unspecified</pose>
		<truncated>0</truncated>
		<difficult>0</difficult>
		<bndbox>
			<xmin>1019</xmin>
			<ymin>980</ymin>
			<xmax>1051</xmax>
			<ymax>1007</ymax>
		</bndbox>
	</object>
</annotation>
