<annotation>
	<folder>images</folder>
	<filename>datum-03999.png</filename>
	<path>C:\Users\Lenovo-PC\OneDrive\Documents\To Annotate\images\datum-03999.png</path>
	<source>
		<database>Unknown</database>
	</source>
	<size>
		<width>1920</width>
		<height>1080</height>
		<depth>3</depth>
	</size>
	<segmented>0</segmented>
	<object>
		<name>tree branch</name>
		<pose>Unspecified</pose>
		<truncated>0</truncated>
		<difficult>0</difficult>
		<bndbox>
			<xmin>483</xmin>
			<ymin>14</ymin>
			<xmax>758</xmax>
			<ymax>802</ymax>
		</bndbox>
	</object>
	<object>
		<name>leaf</name>
		<pose>Unspecified</pose>
		<truncated>0</truncated>
		<difficult>0</difficult>
		<bndbox>
			<xmin>602</xmin>
			<ymin>832</ymin>
			<xmax>636</xmax>
			<ymax>869</ymax>
		</bndbox>
	</object>
</annotation>
