<annotation>
	<folder>images</folder>
	<filename>datum-03366.png</filename>
	<path>C:\Users\Lenovo-PC\OneDrive\Documents\To Annotate\images\datum-03366.png</path>
	<source>
		<database>Unknown</database>
	</source>
	<size>
		<width>1920</width>
		<height>1080</height>
		<depth>3</depth>
	</size>
	<segmented>0</segmented>
	<object>
		<name>tree branch</name>
		<pose>Unspecified</pose>
		<truncated>0</truncated>
		<difficult>0</difficult>
		<bndbox>
			<xmin>826</xmin>
			<ymin>10</ymin>
			<xmax>988</xmax>
			<ymax>1021</ymax>
		</bndbox>
	</object>
	<object>
		<name>leaf</name>
		<pose>Unspecified</pose>
		<truncated>0</truncated>
		<difficult>0</difficult>
		<bndbox>
			<xmin>1042</xmin>
			<ymin>859</ymin>
			<xmax>1086</xmax>
			<ymax>912</ymax>
		</bndbox>
	</object>
	<object>
		<name>leaf</name>
		<pose>Unspecified</pose>
		<truncated>0</truncated>
		<difficult>0</difficult>
		<bndbox>
			<xmin>1410</xmin>
			<ymin>802</ymin>
			<xmax>1458</xmax>
			<ymax>914</ymax>
		</bndbox>
	</object>
	<object>
		<name>leaf</name>
		<pose>Unspecified</pose>
		<truncated>0</truncated>
		<difficult>0</difficult>
		<bndbox>
			<xmin>1367</xmin>
			<ymin>743</ymin>
			<xmax>1431</xmax>
			<ymax>807</ymax>
		</bndbox>
	</object>
	<object>
		<name>branch with leaves</name>
		<pose>Unspecified</pose>
		<truncated>0</truncated>
		<difficult>0</difficult>
		<bndbox>
			<xmin>1319</xmin>
			<ymin>112</ymin>
			<xmax>1647</xmax>
			<ymax>410</ymax>
		</bndbox>
	</object>
</annotation>
