<annotation>
	<folder>images</folder>
	<filename>datum-02147.png</filename>
	<path>C:\Users\Arjie\Documents\To Annotate\images\datum-02147.png</path>
	<source>
		<database>Unknown</database>
	</source>
	<size>
		<width>1920</width>
		<height>1080</height>
		<depth>3</depth>
	</size>
	<segmented>0</segmented>
	<object>
		<name>tree branch</name>
		<pose>Unspecified</pose>
		<truncated>0</truncated>
		<difficult>0</difficult>
		<bndbox>
			<xmin>290</xmin>
			<ymin>313</ymin>
			<xmax>1871</xmax>
			<ymax>1068</ymax>
		</bndbox>
	</object>
	<object>
		<name>tree branch</name>
		<pose>Unspecified</pose>
		<truncated>0</truncated>
		<difficult>0</difficult>
		<bndbox>
			<xmin>1582</xmin>
			<ymin>848</ymin>
			<xmax>1811</xmax>
			<ymax>909</ymax>
		</bndbox>
	</object>
	<object>
		<name>tree branch</name>
		<pose>Unspecified</pose>
		<truncated>0</truncated>
		<difficult>0</difficult>
		<bndbox>
			<xmin>1474</xmin>
			<ymin>954</ymin>
			<xmax>1511</xmax>
			<ymax>997</ymax>
		</bndbox>
	</object>
	<object>
		<name>tree branch</name>
		<pose>Unspecified</pose>
		<truncated>0</truncated>
		<difficult>0</difficult>
		<bndbox>
			<xmin>1340</xmin>
			<ymin>813</ymin>
			<xmax>1392</xmax>
			<ymax>838</ymax>
		</bndbox>
	</object>
	<object>
		<name>tree branch</name>
		<pose>Unspecified</pose>
		<truncated>0</truncated>
		<difficult>0</difficult>
		<bndbox>
			<xmin>1363</xmin>
			<ymin>836</ymin>
			<xmax>1395</xmax>
			<ymax>949</ymax>
		</bndbox>
	</object>
	<object>
		<name>tree branch</name>
		<pose>Unspecified</pose>
		<truncated>0</truncated>
		<difficult>0</difficult>
		<bndbox>
			<xmin>1310</xmin>
			<ymin>913</ymin>
			<xmax>1356</xmax>
			<ymax>980</ymax>
		</bndbox>
	</object>
	<object>
		<name>mahogany fruit</name>
		<pose>Unspecified</pose>
		<truncated>0</truncated>
		<difficult>0</difficult>
		<bndbox>
			<xmin>1472</xmin>
			<ymin>916</ymin>
			<xmax>1540</xmax>
			<ymax>981</ymax>
		</bndbox>
	</object>
	<object>
		<name>mahogany fruit</name>
		<pose>Unspecified</pose>
		<truncated>0</truncated>
		<difficult>0</difficult>
		<bndbox>
			<xmin>1446</xmin>
			<ymin>1001</ymin>
			<xmax>1521</xmax>
			<ymax>1070</ymax>
		</bndbox>
	</object>
	<object>
		<name>leaf</name>
		<pose>Unspecified</pose>
		<truncated>0</truncated>
		<difficult>0</difficult>
		<bndbox>
			<xmin>1395</xmin>
			<ymin>988</ymin>
			<xmax>1446</xmax>
			<ymax>1023</ymax>
		</bndbox>
	</object>
	<object>
		<name>tree branch</name>
		<pose>Unspecified</pose>
		<truncated>0</truncated>
		<difficult>0</difficult>
		<bndbox>
			<xmin>1579</xmin>
			<ymin>914</ymin>
			<xmax>1703</xmax>
			<ymax>1020</ymax>
		</bndbox>
	</object>
	<object>
		<name>tree branch</name>
		<pose>Unspecified</pose>
		<truncated>0</truncated>
		<difficult>0</difficult>
		<bndbox>
			<xmin>1526</xmin>
			<ymin>968</ymin>
			<xmax>1600</xmax>
			<ymax>996</ymax>
		</bndbox>
	</object>
</annotation>
