<annotation>
	<folder>images</folder>
	<filename>datum-05879.png</filename>
	<path>C:\Users\User\OneDrive\General\Documents\For Annotation\images\datum-05879.png</path>
	<source>
		<database>Unknown</database>
	</source>
	<size>
		<width>1920</width>
		<height>1080</height>
		<depth>3</depth>
	</size>
	<segmented>0</segmented>
	<object>
		<name>leaf</name>
		<pose>Unspecified</pose>
		<truncated>0</truncated>
		<difficult>0</difficult>
		<bndbox>
			<xmin>974</xmin>
			<ymin>617</ymin>
			<xmax>1074</xmax>
			<ymax>736</ymax>
		</bndbox>
	</object>
	<object>
		<name>tree branch</name>
		<pose>Unspecified</pose>
		<truncated>0</truncated>
		<difficult>0</difficult>
		<bndbox>
			<xmin>1241</xmin>
			<ymin>274</ymin>
			<xmax>1762</xmax>
			<ymax>542</ymax>
		</bndbox>
	</object>
	<object>
		<name>tree branch</name>
		<pose>Unspecified</pose>
		<truncated>1</truncated>
		<difficult>0</difficult>
		<bndbox>
			<xmin>1239</xmin>
			<ymin>1</ymin>
			<xmax>1363</xmax>
			<ymax>257</ymax>
		</bndbox>
	</object>
	<object>
		<name>branch with leaves</name>
		<pose>Unspecified</pose>
		<truncated>0</truncated>
		<difficult>0</difficult>
		<bndbox>
			<xmin>1237</xmin>
			<ymin>299</ymin>
			<xmax>1695</xmax>
			<ymax>453</ymax>
		</bndbox>
	</object>
	<object>
		<name>leaf</name>
		<pose>Unspecified</pose>
		<truncated>0</truncated>
		<difficult>0</difficult>
		<bndbox>
			<xmin>1699</xmin>
			<ymin>319</ymin>
			<xmax>1781</xmax>
			<ymax>413</ymax>
		</bndbox>
	</object>
	<object>
		<name>mahogany fruit</name>
		<pose>Unspecified</pose>
		<truncated>0</truncated>
		<difficult>0</difficult>
		<bndbox>
			<xmin>1168</xmin>
			<ymin>401</ymin>
			<xmax>1297</xmax>
			<ymax>561</ymax>
		</bndbox>
	</object>
</annotation>
