<annotation>
	<folder>images</folder>
	<filename>datum-06139.png</filename>
	<path>C:\Users\User\OneDrive\General\Documents\For Annotation\images\datum-06139.png</path>
	<source>
		<database>Unknown</database>
	</source>
	<size>
		<width>1920</width>
		<height>1440</height>
		<depth>3</depth>
	</size>
	<segmented>0</segmented>
	<object>
		<name>tree branch</name>
		<pose>Unspecified</pose>
		<truncated>0</truncated>
		<difficult>0</difficult>
		<bndbox>
			<xmin>972</xmin>
			<ymin>451</ymin>
			<xmax>1888</xmax>
			<ymax>691</ymax>
		</bndbox>
	</object>
	<object>
		<name>tree branch</name>
		<pose>Unspecified</pose>
		<truncated>0</truncated>
		<difficult>0</difficult>
		<bndbox>
			<xmin>1074</xmin>
			<ymin>595</ymin>
			<xmax>1245</xmax>
			<ymax>666</ymax>
		</bndbox>
	</object>
	<object>
		<name>branch with leaves</name>
		<pose>Unspecified</pose>
		<truncated>0</truncated>
		<difficult>0</difficult>
		<bndbox>
			<xmin>1063</xmin>
			<ymin>491</ymin>
			<xmax>1688</xmax>
			<ymax>806</ymax>
		</bndbox>
	</object>
	<object>
		<name>leaf</name>
		<pose>Unspecified</pose>
		<truncated>0</truncated>
		<difficult>0</difficult>
		<bndbox>
			<xmin>1110</xmin>
			<ymin>573</ymin>
			<xmax>1194</xmax>
			<ymax>644</ymax>
		</bndbox>
	</object>
	<object>
		<name>mahogany fruit</name>
		<pose>Unspecified</pose>
		<truncated>0</truncated>
		<difficult>0</difficult>
		<bndbox>
			<xmin>1257</xmin>
			<ymin>486</ymin>
			<xmax>1470</xmax>
			<ymax>629</ymax>
		</bndbox>
	</object>
</annotation>
