<annotation>
	<folder>images</folder>
	<filename>datum-03379.png</filename>
	<path>C:\Users\Lenovo-PC\OneDrive\Documents\To Annotate\images\datum-03379.png</path>
	<source>
		<database>Unknown</database>
	</source>
	<size>
		<width>1920</width>
		<height>1080</height>
		<depth>3</depth>
	</size>
	<segmented>0</segmented>
	<object>
		<name>tree branch</name>
		<pose>Unspecified</pose>
		<truncated>0</truncated>
		<difficult>0</difficult>
		<bndbox>
			<xmin>760</xmin>
			<ymin>2</ymin>
			<xmax>910</xmax>
			<ymax>809</ymax>
		</bndbox>
	</object>
	<object>
		<name>leaf</name>
		<pose>Unspecified</pose>
		<truncated>0</truncated>
		<difficult>0</difficult>
		<bndbox>
			<xmin>886</xmin>
			<ymin>652</ymin>
			<xmax>931</xmax>
			<ymax>684</ymax>
		</bndbox>
	</object>
	<object>
		<name>leaf</name>
		<pose>Unspecified</pose>
		<truncated>0</truncated>
		<difficult>0</difficult>
		<bndbox>
			<xmin>1195</xmin>
			<ymin>618</ymin>
			<xmax>1245</xmax>
			<ymax>659</ymax>
		</bndbox>
	</object>
	<object>
		<name>leaf</name>
		<pose>Unspecified</pose>
		<truncated>0</truncated>
		<difficult>0</difficult>
		<bndbox>
			<xmin>1140</xmin>
			<ymin>593</ymin>
			<xmax>1188</xmax>
			<ymax>641</ymax>
		</bndbox>
	</object>
	<object>
		<name>branch with leaves</name>
		<pose>Unspecified</pose>
		<truncated>0</truncated>
		<difficult>0</difficult>
		<bndbox>
			<xmin>1145</xmin>
			<ymin>96</ymin>
			<xmax>1406</xmax>
			<ymax>355</ymax>
		</bndbox>
	</object>
</annotation>
